bpyshell/__init__.py
bpyshell/_nbdev.py
bpyshell/core.py
pyshell/__init__.py
pyshell/_nbdev.py
pyshell/core.py
bpyshell-0.0.6.dist-info/LICENSE
bpyshell-0.0.6.dist-info/METADATA
bpyshell-0.0.6.dist-info/WHEEL
bpyshell-0.0.6.dist-info/top_level.txt
bpyshell-0.0.6.dist-info/RECORD
