Metadata-Version: 2.1
Name: bpyshell
Version: 0.0.6
Summary: A Shell object
Home-page: https://github.com/ababino/bpyshell/tree/master/
Author: Andres Babino
Author-email: ababino@gmail.com
License: Apache Software License 2.0
Keywords: python shell
Classifier: Development Status :: 3 - Alpha
Classifier: Intended Audience :: Developers
Classifier: Natural Language :: English
Classifier: Programming Language :: Python :: 3.7
Classifier: Programming Language :: Python :: 3.8
Classifier: Programming Language :: Python :: 3.9
Classifier: Programming Language :: Python :: 3.10
Classifier: License :: OSI Approved :: Apache Software License
Requires-Python: >=3.7
License-File: LICENSE
Requires-Dist: pip
Requires-Dist: packaging
Requires-Dist: fastcore
Provides-Extra: dev
